fame/main.py
fame/FVM/__init__.py
fame/FVM/boundaryCondition.py
fame/FVM/discretization.py
fame/FVM/finiteVolumeMethod.py
fame/FVM/mesh.py
fame/FVM/physics.py
fame/FVM/property.py
fame/FVM/solver.py
fame/FVM/visualization.py
fame_ud-0.0.5.dist-info/METADATA
fame_ud-0.0.5.dist-info/WHEEL
fame_ud-0.0.5.dist-info/entry_points.txt
fame_ud-0.0.5.dist-info/licenses/LICENSE
fame_ud-0.0.5.dist-info/RECORD
