Metadata-Version: 2.4
Name: FAME-UD
Version: 0.0.5
Summary: A framework for emulating additive manufacturing processes.
Project-URL: Homepage, https://github.com/neoceph/FAME
Project-URL: Issues, https://github.com/neoceph/FAME/issues
Author-email: Abdullah_Al_Amin <nirjhor18@gmail.com>
License-File: LICENSE
Classifier: License :: OSI Approved :: MIT License
Classifier: Operating System :: OS Independent
Classifier: Programming Language :: Python :: 3
Requires-Python: >=3.8
